[
  {
    "id": 1,
    "authorId": 1,
    "authorName" : "John Doe",
    "authorImage" : "images/default-avatar.jpg",
    "createdAt": "2025",
    "postText" : "Lorem ipsum dolor sit amet consectetur adipisicing elit. Quas, voluptate?",
    "postHearts" : 10,
    "postLikes" : 1200,
    "postDislikes" : 100,
    "postComments" : 3,
    "liked" : 0,
    "observed" : true,
    "saved" : false
  },
  {
    "id": 2,
    "authorId": 2,
    "authorName" : "Anna Boe",
    "authorImage" : "images/default-avatar.jpg",
    "createdAt": "202",
    "postText" : "Lorem ipsum dolor sit amet consectetur adipisicing elit. Quas, voluptate?",
    "postHearts" : 1,
    "postLikes" : 2,
    "postDislikes" : 100,
    "postComments" : 3,
    "liked" : 1,
    "observed" : false,
    "saved" : false
  }
  ,
    {
    "id": 3,
    "authorId": 2,
    "authorName" : "Anna Boe",
    "authorImage" : "images/default-avatar.jpg",
    "createdAt": "202",
    "postText" : "Lorem ipsum dolor sit amet consectetur adipisicing elit. Quas, voluptate?",
    "postHearts" : 0,
    "postLikes" : 2,
    "postDislikes" : 100,
    "postComments" : 3,
    "liked" : 2,
    "observed" : false
  },
      {
    "id": 4,
    "authorId": 3,
    "authorName" : "Ewan More",
    "authorImage" : "images/default-avatar.jpg",
    "createdAt": "202",
    "postText" : "Lorem ipsum dolor sit amet consectetur adipisicing elit. Quas, voluptate?",
    "postHearts" : 0,
    "postLikes" : 2,
    "postDislikes" : 100,
    "postComments" : 3,
    "liked" : 3,
    "observed" : false
  },
    {
    "id": 5,
    "authorId": 2,
    "authorName" : "Anna Boe",
    "authorImage" : "images/default-avatar.jpg",
    "createdAt": "202",
    "postText" : "Lorem ipsum dolor sit amet consectetur adipisicing elit. Quas, voluptate?",
    "postHearts" : 1,
    "postLikes" : 2,
    "postDislikes" : 100,
    "postComments" : 3,
    "liked" : 1,
    "observed" : false,
    "saved" : true
  },
    {
    "id": 6,
    "authorId": 2,
    "authorName" : "Anna Boe",
    "authorImage" : "images/default-avatar.jpg",
    "createdAt": "202",
    "postText" : "Lorem ipsum dolor sit amet consectetur adipisicing elit. Quas, voluptate?",
    "postHearts" : 1,
    "postLikes" : 2,
    "postDislikes" : 100,
    "postComments" : 3,
    "liked" : 1,
    "observed" : false,
    "saved" : true
  },
    {
    "id": 7,
    "authorId": 2,
    "authorName" : "Anna Boe",
    "authorImage" : "images/default-avatar.jpg",
    "createdAt": "202",
    "postText" : "Lorem ipsum dolor sit amet consectetur adipisicing elit. Quas, voluptate?",
    "postHearts" : 1,
    "postLikes" : 2,
    "postDislikes" : 100,
    "postComments" : 3,
    "liked" : 1,
    "observed" : false,
    "saved" : true
  }

]